CHANGELOG.rst
MANIFEST.in
README.rst
setup.py
SecretStorage_Setup.egg-info/PKG-INFO
SecretStorage_Setup.egg-info/SOURCES.txt
SecretStorage_Setup.egg-info/dependency_links.txt
SecretStorage_Setup.egg-info/entry_points.txt
SecretStorage_Setup.egg-info/not-zip-safe
SecretStorage_Setup.egg-info/requires.txt
SecretStorage_Setup.egg-info/top_level.txt
sssetup/__init__.py
sssetup/cli.py
sssetup/core.py
sssetup/version.py
sssetup/tests/__init__.py
sssetup/tests/tox_functional.py