Metadata-Version: 1.1
Name: SecretStorage-Setup
Version: 0.1.1
Summary: Ease setup of SecretStorage in virtualenvs
Home-page: https://github.com/level12/secretstorage-setup
Author: Randy Syring
Author-email: randy.syring@level12.io
License: BSD
Platform: UNKNOWN
Classifier: Development Status :: 4 - Beta
Classifier: Intended Audience :: Developers
Classifier: License :: OSI Approved :: BSD License
Classifier: Operating System :: POSIX :: Linux
Classifier: Programming Language :: Python :: 2.7
Classifier: Programming Language :: Python :: 3
Classifier: Programming Language :: Python :: 3.4
